MANIFEST.in
board_purchase_view.xml
company_view.xml
partner_view.xml
purchase_data.xml
purchase_demo.xml
purchase_order_demo.yml
purchase_report.xml
purchase_sequence.xml
purchase_view.xml
purchase_workflow.xml
res_config_view.xml
setup.py
stock_view.xml
./__init__.py
./__openerp__.py
./company.py
./partner.py
./purchase.py
./res_config.py
./stock.py
./edi/__init__.py
./edi/purchase_order.py
./report/__init__.py
./report/order.py
./report/purchase_report.py
./report/request_quotation.py
./wizard/__init__.py
./wizard/purchase_line_invoice.py
./wizard/purchase_order_group.py
edi/purchase_order_action_data.xml
i18n/ar.po
i18n/bg.po
i18n/bs.po
i18n/ca.po
i18n/cs.po
i18n/da.po
i18n/de.po
i18n/el.po
i18n/en_GB.po
i18n/es.po
i18n/es_AR.po
i18n/es_BO.po
i18n/es_CL.po
i18n/es_CO.po
i18n/es_CR.po
i18n/es_EC.po
i18n/es_MX.po
i18n/es_PE.po
i18n/es_VE.po
i18n/et.po
i18n/fi.po
i18n/fr.po
i18n/gl.po
i18n/hr.po
i18n/hu.po
i18n/id.po
i18n/it.po
i18n/ja.po
i18n/ko.po
i18n/lt.po
i18n/lv.po
i18n/mk.po
i18n/mn.po
i18n/nb.po
i18n/nl.po
i18n/nl_BE.po
i18n/pl.po
i18n/pt.po
i18n/pt_BR.po
i18n/purchase.pot
i18n/ro.po
i18n/ru.po
i18n/sk.po
i18n/sl.po
i18n/sq.po
i18n/sr.po
i18n/sr@latin.po
i18n/sv.po
i18n/th.po
i18n/tlh.po
i18n/tr.po
i18n/uk.po
i18n/vi.po
i18n/zh_CN.po
i18n/zh_TW.po
images/purchase_analysis.jpeg
images/purchase_order.jpeg
images/purchases-hover.png
images/purchases.png
images/request_for_quotation.jpeg
openerp_purchase.egg-info/PKG-INFO
openerp_purchase.egg-info/SOURCES.txt
openerp_purchase.egg-info/dependency_links.txt
openerp_purchase.egg-info/requires.txt
openerp_purchase.egg-info/top_level.txt
process/purchase_process.xml
report/order.rml
report/order.sxw
report/purchase_report_view.xml
report/request_quotation.rml
report/request_quotation.sxw
security/ir.model.access.csv
security/purchase_security.xml
static/src/img/icon.png
test/process/cancel_order.yml
test/process/edi_purchase_order.yml
test/process/generate_invoice_from_reception.yml
test/process/invoice_on_poline.yml
test/process/merge_order.yml
test/process/rfq2order2done.yml
test/process/run_scheduler.yml
test/ui/delete_order.yml
test/ui/duplicate_order.yml
test/ui/print_report.yml
